LICENSE.txt
README.md
pyproject.toml
setup.cfg
setup.py
cli_color_py/__init__.py
cli_color_py/color.py
cli_color_py.egg-info/PKG-INFO
cli_color_py.egg-info/SOURCES.txt
cli_color_py.egg-info/dependency_links.txt
cli_color_py.egg-info/top_level.txt