Metadata-Version: 2.1
Name: cli-color-py
Version: 0.3.0
Summary: Minimalistic way to add colors to your terminal output
Home-page: https://github.com/jasonverbeek/cli-color-py
Download-URL: https://github.com/jasonverbeek/cli-color-py/archive/refs/tags/0.3.0.tar.gz
Author: Jason Verbeek
Author-email: jason@localhost8080.org
License: UNKNOWN
Platform: UNKNOWN
Classifier: Development Status :: 3 - Alpha
Classifier: Programming Language :: Python :: 3.8
Classifier: Programming Language :: Python :: 3.9
Classifier: Programming Language :: Python :: 3.10
License-File: LICENSE.txt
